fractime/__init__.py
fractime/_numba.py
fractime/analyzer.py
fractime/ensemble.py
fractime/forecaster.py
fractime/result.py
fractime/simulator.py
fractime/visualization.py
fractime/_deprecated/_ensemble_old.py
fractime/_deprecated/_simulation_old.py
fractime/_deprecated/_visualization_old.py
fractime/_deprecated/analysis.py
fractime/_deprecated/backtester.py
fractime/_deprecated/core.py
fractime/_deprecated/data_loader.py
fractime/_deprecated/exogenous.py
fractime/_deprecated/optimization.py
fractime/_deprecated/utils.py
fractime/_deprecated/backtesting/__init__.py
fractime/_deprecated/backtesting/metrics.py
fractime/_deprecated/backtesting/scoring.py
fractime/_deprecated/backtesting/validator.py
fractime/_deprecated/data_sources/__init__.py
fractime/_deprecated/data_sources/base.py
fractime/_deprecated/data_sources/crypto.py
fractime/_deprecated/data_sources/economic.py
fractime/_deprecated/data_sources/equities.py
fractime/_deprecated/data_sources/other.py
fractime/_deprecated/data_sources/registry.py
fractime/baselines/__init__.py
fractime/baselines/arima.py
fractime/baselines/ets.py
fractime/baselines/garch.py
fractime/baselines/lstm.py
fractime/baselines/prophet.py
fractime/baselines/var.py
fractime/bayesian/__init__.py
fractime/bayesian/forecaster.py
fractime/bayesian/models.py
fractime/bayesian/samplers.py
fractime/forecasting/__init__.py
fractime/forecasting/base.py
fractime/forecasting/fractal.py
fractime/forecasting/ml.py
fractime/forecasting/statistical.py
fractime/selection/__init__.py
fractime/selection/ensemble.py
fractime/selection/registry.py
fractime/selection/selector.py
fractime/selection/statistical_tests.py
fractime-0.4.0.dist-info/METADATA
fractime-0.4.0.dist-info/WHEEL
fractime-0.4.0.dist-info/RECORD
