Metadata-Version: 2.4
Name: fractime
Version: 0.4.0
Summary: Python library for advanced time series forecasting using fractal geometry and chaos theory
Project-URL: Homepage, https://github.com/Wayy-Research/fracTime
Project-URL: Documentation, https://wayy-research.github.io/fracTime
Project-URL: Repository, https://github.com/Wayy-Research/fracTime
Project-URL: Issues, https://github.com/Wayy-Research/fracTime/issues
Author-email: RC Galbo <rcgalbo@gmail.com>
License: MIT
Keywords: chaos-theory,finance,forecasting,fractals,hurst-exponent,quantitative-finance,time-series
Classifier: Development Status :: 4 - Beta
Classifier: Intended Audience :: Science/Research
Classifier: License :: OSI Approved :: MIT License
Classifier: Programming Language :: Python :: 3.10
Classifier: Programming Language :: Python :: 3.11
Classifier: Programming Language :: Python :: 3.12
Classifier: Topic :: Office/Business :: Financial
Classifier: Topic :: Scientific/Engineering :: Mathematics
Requires-Python: >=3.10
Requires-Dist: arch>=6.0.0
Requires-Dist: arviz>=0.18.0
Requires-Dist: matplotlib>=3.10.0
Requires-Dist: numba>=0.61.0
Requires-Dist: numpy>=2.1.3
Requires-Dist: pandas>=2.2.3
Requires-Dist: pmdarima>=2.0.0
Requires-Dist: polars>=1.22.0
Requires-Dist: prophet>=1.1.0
Requires-Dist: pyarrow>=19.0.1
Requires-Dist: pymc>=5.10.0
Requires-Dist: pytensor>=2.18.0
Requires-Dist: requests>=2.32.3
Requires-Dist: scikit-learn>=1.6.1
Requires-Dist: scipy>=1.15.2
Requires-Dist: statsmodels>=0.14.4
Requires-Dist: wrchart>=0.1.0
Requires-Dist: xgboost>=2.0.0
Requires-Dist: yfinance>=0.2.54
Provides-Extra: dev
Requires-Dist: black>=24.2.0; extra == 'dev'
Requires-Dist: mypy>=1.8.0; extra == 'dev'
Requires-Dist: pytest-cov>=4.1.0; extra == 'dev'
Requires-Dist: pytest>=8.0.0; extra == 'dev'
Requires-Dist: ruff>=0.3.0; extra == 'dev'
Provides-Extra: docs
Requires-Dist: mkdocs-gen-files>=0.5.0; extra == 'docs'
Requires-Dist: mkdocs-literate-nav>=0.6.0; extra == 'docs'
Requires-Dist: mkdocs-material>=9.5.0; extra == 'docs'
Requires-Dist: mkdocs>=1.6.0; extra == 'docs'
Requires-Dist: mkdocstrings[python]>=0.24.0; extra == 'docs'
